compango/__init__.py
compango-0.0.1.dist-info/licenses/LICENCE
compango-0.0.1.dist-info/METADATA
compango-0.0.1.dist-info/WHEEL
compango-0.0.1.dist-info/top_level.txt
compango-0.0.1.dist-info/RECORD
