Metadata-Version: 2.4
Name: compango
Version: 0.0.1
Summary: HTMX components for django
Home-page: https://github.com/caullla/compango
Author: Oleksandr Sorokin
Author-email: bsorokind@gmail.com
Classifier: Programming Language :: Python :: 3
Classifier: License :: OSI Approved :: MIT License
Requires-Python: >=3.10
License-File: LICENCE
Dynamic: author
Dynamic: author-email
Dynamic: classifier
Dynamic: description
Dynamic: description-content-type
Dynamic: home-page
Dynamic: license-file
Dynamic: requires-python
Dynamic: summary
